glue/__init__.py
glue/_mpl_backend.py
glue/_plugin_helpers.py
glue/_settings_helpers.py
glue/backends.py
glue/config.py
glue/config_gen.py
glue/conftest.py
glue/default_config.py
glue/logger.py
glue/logo.png
glue/main.py
glue/app/__init__.py
glue/app/tests/__init__.py
glue/core/__init__.py
glue/core/aggregate.py
glue/core/application_base.py
glue/core/autolinking.py
glue/core/callback_property.py
glue/core/command.py
glue/core/component.py
glue/core/component_id.py
glue/core/component_link.py
glue/core/contracts.py
glue/core/coordinate_helpers.py
glue/core/coordinates.py
glue/core/data.py
glue/core/data_collection.py
glue/core/data_combo_helper.py
glue/core/data_derived.py
glue/core/data_region.py
glue/core/decorators.py
glue/core/edit_subset_mode.py
glue/core/exceptions.py
glue/core/fitters.py
glue/core/fixed_resolution_buffer.py
glue/core/glue_pickle.py
glue/core/hub.py
glue/core/hub_callback_container.py
glue/core/joins.py
glue/core/layer_artist.py
glue/core/layout.py
glue/core/link_helpers.py
glue/core/link_manager.py
glue/core/message.py
glue/core/parse.py
glue/core/regions.py
glue/core/registry.py
glue/core/roi.py
glue/core/roi_pretransforms.py
glue/core/session.py
glue/core/simpleforms.py
glue/core/state.py
glue/core/state_objects.py
glue/core/state_path_patches.txt
glue/core/subset.py
glue/core/subset_group.py
glue/core/units.py
glue/core/util.py
glue/core/visual.py
glue/core/data_exporters/__init__.py
glue/core/data_exporters/astropy_table.py
glue/core/data_exporters/gridded_fits.py
glue/core/data_exporters/hdf5.py
glue/core/data_exporters/tests/__init__.py
glue/core/data_exporters/tests/test_astropy_table.py
glue/core/data_exporters/tests/test_gridded_fits.py
glue/core/data_exporters/tests/test_hdf5.py
glue/core/data_factories/__init__.py
glue/core/data_factories/astropy_table.py
glue/core/data_factories/dendrogram.py
glue/core/data_factories/deprecated.py
glue/core/data_factories/excel.py
glue/core/data_factories/fits.py
glue/core/data_factories/hdf5.py
glue_core-1.24.1.dist-info/licenses/LICENSE
glue_core-1.24.1.dist-info/METADATA
glue_core-1.24.1.dist-info/WHEEL
glue_core-1.24.1.dist-info/entry_points.txt
glue_core-1.24.1.dist-info/top_level.txt
glue_core-1.24.1.dist-info/RECORD
