Metadata-Version: 2.4
Name: glue-core
Version: 1.24.1
Summary: Core library for the glue multidimensional data visualization project
Home-page: http://glueviz.org
Author: Thomas Robitaille, Chris Beaumont
Author-email: glueviz@gmail.com
Classifier: Intended Audience :: Science/Research
Classifier: Operating System :: OS Independent
Classifier: Programming Language :: Python
Classifier: Programming Language :: Python :: 3
Classifier: Programming Language :: Python :: 3.10
Classifier: Programming Language :: Python :: 3.11
Classifier: Programming Language :: Python :: 3.12
Classifier: Programming Language :: Python :: 3.13
Classifier: Topic :: Scientific/Engineering :: Visualization
Classifier: License :: OSI Approved :: BSD License
Requires-Python: >=3.10
License-File: LICENSE
Requires-Dist: numpy>=1.17
Requires-Dist: matplotlib>=3.2
Requires-Dist: scipy>=1.1
Requires-Dist: pandas>=1.2
Requires-Dist: echo>=0.6
Requires-Dist: astropy>=4.0
Requires-Dist: fast_histogram>=0.12
Requires-Dist: ipython>=4.0
Requires-Dist: dill>=0.2
Requires-Dist: h5py>=2.10
Requires-Dist: xlrd>=1.2
Requires-Dist: openpyxl>=3.0
Requires-Dist: mpl-scatter-density>=0.8
Requires-Dist: importlib_resources>=1.3; python_version < "3.9"
Requires-Dist: importlib_metadata>=3.6; python_version < "3.10"
Requires-Dist: shapely>=2.0
Provides-Extra: all
Requires-Dist: scipy; extra == "all"
Requires-Dist: scikit-image; extra == "all"
Requires-Dist: PyAVM; extra == "all"
Requires-Dist: astrodendro; extra == "all"
Requires-Dist: spectral-cube; extra == "all"
Requires-Dist: pillow!=7.1.0; extra == "all"
Provides-Extra: docs
Requires-Dist: sphinx<7; extra == "docs"
Requires-Dist: sphinx-automodapi; extra == "docs"
Requires-Dist: sphinxcontrib-spelling; extra == "docs"
Requires-Dist: numpydoc; extra == "docs"
Requires-Dist: sphinx-book-theme; extra == "docs"
Provides-Extra: astronomy
Requires-Dist: PyAVM; extra == "astronomy"
Requires-Dist: astrodendro; extra == "astronomy"
Requires-Dist: spectral-cube; extra == "astronomy"
Provides-Extra: recommended
Requires-Dist: scikit-image; extra == "recommended"
Provides-Extra: test
Requires-Dist: pytest; extra == "test"
Requires-Dist: pytest-cov; extra == "test"
Requires-Dist: pytest-faulthandler; extra == "test"
Requires-Dist: pytest-flake8; extra == "test"
Requires-Dist: h5py>=2.10; platform_system == "Linux" and extra == "test"
Requires-Dist: objgraph; extra == "test"
Provides-Extra: visualtest
Requires-Dist: pytest-mpl; extra == "visualtest"
Dynamic: license-file
